setup.py
messenger_server.egg-info/PKG-INFO
messenger_server.egg-info/SOURCES.txt
messenger_server.egg-info/dependency_links.txt
messenger_server.egg-info/requires.txt
messenger_server.egg-info/top_level.txt
server/__init__.py
server/server.py
server/common/__init__.py
server/common/decorators.py
server/common/descryptors.py
server/common/errors.py
server/common/functions.py
server/common/metaclasses.py
server/common/variables.py
server/log/__init__.py
server/log/config_client_log.py
server/log/config_server_log.py
server/server/__init__.py
server/server/add_user.py
server/server/config_window.py
server/server/core.py
server/server/database.py
server/server/main_window.py
server/server/remove_user.py
server/server/stat_window.py
server/test/__init__.py