Metadata-Version: 1.0
Name: messenger-server
Version: 0.0.1
Summary: Messenger_Server
Home-page: UNKNOWN
Author: Ilia Niyazof
Author-email: iv.iv@yandex.ru
License: UNKNOWN
Platform: UNKNOWN
